Metadata-Version: 1.0
Name: barman-exporter
Version: 1.0.7
Summary: Barman exporter for Prometheus
Home-page: https://github.com/ahes/prometheus-barman-exporter
Author: Marcin Hlybin
Author-email: marcin.hlybin@gmail.com
License: MIT
Keywords: prometheus barman exporter barman-exporter
Platform: UNKNOWN
